static_typing/__init__.py
static_typing/_logging.py
static_typing/_version.py
static_typing/augment.py
static_typing/generic.py
static_typing/numpy_types.py
static_typing/parse.py
static_typing/py.typed
static_typing/static_typer.py
static_typing/unparse.py
static_typing/unparser.py
static_typing/ast_manipulation/__init__.py
static_typing/ast_manipulation/ast_transcriber.py
static_typing/ast_manipulation/ast_validator.py
static_typing/ast_manipulation/recursive_ast_transformer.py
static_typing/ast_manipulation/recursive_ast_visitor.py
static_typing/ast_manipulation/type_hint_resolver.py
static_typing/nodes/__init__.py
static_typing/nodes/class_def.py
static_typing/nodes/context.py
static_typing/nodes/declaration.py
static_typing/nodes/function_def.py
static_typing/nodes/module.py
static_typing/nodes/statically_typed.py
static_typing-0.2.7.dist-info/LICENSE
static_typing-0.2.7.dist-info/METADATA
static_typing-0.2.7.dist-info/NOTICE
static_typing-0.2.7.dist-info/WHEEL
static_typing-0.2.7.dist-info/top_level.txt
static_typing-0.2.7.dist-info/RECORD
