Metadata-Version: 2.1
Name: static-typing
Version: 0.2.7
Summary: add static type information to Python abstract syntax trees
Home-page: https://github.com/mbdevpl/static-typing
Author: Mateusz Bysiek
Author-email: mateusz.bysiek@gmail.com
Maintainer: Mateusz Bysiek
Maintainer-email: mateusz.bysiek@gmail.com
License: Apache License 2.0
Keywords: ast,parser,parsing,static type information,type analysis,types,typing
Platform: UNKNOWN
Classifier: Development Status :: 1 - Planning
Classifier: Environment :: Console
Classifier: Intended Audience :: Developers
Classifier: Intended Audience :: Science/Research
Classifier: License :: OSI Approved :: Apache Software License
Classifier: Natural Language :: English
Classifier: Operating System :: Microsoft :: Windows
Classifier: Operating System :: POSIX :: Linux
Classifier: Programming Language :: Python :: 3.5
Classifier: Programming Language :: Python :: 3.6
Classifier: Programming Language :: Python :: 3.7
Classifier: Programming Language :: Python :: 3 :: Only
Classifier: Topic :: Education
Classifier: Topic :: Scientific/Engineering
Classifier: Topic :: Utilities
Requires-Python: >=3.5
Requires-Dist: numpy
Requires-Dist: ordered-set
Requires-Dist: typed-ast (>=1.4.0)
Requires-Dist: typed-astunparse (>=2.1.4)
Requires-Dist: version-query
